fpsl/__init__.py
fpsl/py.typed
fpsl/datasets/__init__.py
fpsl/datasets/datasets.py
fpsl/datasets/potentials.py
fpsl/ddm/__init__.py
fpsl/ddm/forceschedule.py
fpsl/ddm/models.py
fpsl/ddm/network.py
fpsl/ddm/noiseschedule.py
fpsl/ddm/prior.py
fpsl/ddm/priorschedule.py
fpsl/utils/__init__.py
fpsl/utils/baseclass.py
fpsl/utils/gmm.py
fpsl/utils/integrators.py
fpsl/utils/typing.py
fpsl-0.2.0.dist-info/METADATA
fpsl-0.2.0.dist-info/WHEEL
fpsl-0.2.0.dist-info/licenses/LICENSE
fpsl-0.2.0.dist-info/RECORD
