Metadata-Version: 2.4
Name: fpsl
Version: 0.2.0
Summary: Fokker-Planck Score Learning: Efficient free-energy estimation under periodic boundary conditions
Project-URL: Documentation, https://BereauLab.github.io/fokker-planck-score-learning
Project-URL: Repository, https://github.com/BereauLab/fokker-planck-score-learning
Project-URL: Issues, https://github.com/BereauLab/fokker-planck-score-learning/issues
Project-URL: Changelog, https://BereauLab.github.io/fokker-planck-score-learning/changelog
Author: braniii
License-Expression: MIT
License-File: LICENSE
Keywords: diffusion model,fokker-planck,free-energy estimation,jax,machine-learning,score-learning
Classifier: Development Status :: 4 - Beta
Classifier: Intended Audience :: Developers
Classifier: Programming Language :: Python :: 3
Classifier: Programming Language :: Python :: 3.10
Classifier: Programming Language :: Python :: 3.11
Classifier: Programming Language :: Python :: 3.12
Classifier: Programming Language :: Python :: 3.13
Classifier: Topic :: Software Development :: Build Tools
Requires-Python: >=3.10
Requires-Dist: beartype>=0.21.0
Requires-Dist: flax>=0.10.6
Requires-Dist: jax-dataloader>=0.1.3
Requires-Dist: jax[cuda,cuda12]==0.6.0
Requires-Dist: jaxtyping>=0.2.36
Requires-Dist: matplotlib>=3.10.3
Requires-Dist: optax>=0.2.5
Requires-Dist: tqdm>=4.67.1
Requires-Dist: wandb>=0.20.1
Provides-Extra: cuda
Requires-Dist: jax[cuda12]>=0.6.0; extra == 'cuda'
Provides-Extra: tpu
Requires-Dist: jax[tpu]>=0.6.0; extra == 'tpu'
